cvxgraphalgs/__init__.py
cvxgraphalgs/algorithms/__init__.py
cvxgraphalgs/algorithms/independent_set.py
cvxgraphalgs/algorithms/max_cut.py
cvxgraphalgs/generators/__init__.py
cvxgraphalgs/generators/planted_models.py
cvxgraphalgs/generators/stochastic_block.py
cvxgraphalgs/structures/__init__.py
cvxgraphalgs/structures/cut.py
cvxgraphalgs-0.1.2.dist-info/LICENSE
cvxgraphalgs-0.1.2.dist-info/METADATA
cvxgraphalgs-0.1.2.dist-info/WHEEL
cvxgraphalgs-0.1.2.dist-info/top_level.txt
cvxgraphalgs-0.1.2.dist-info/RECORD
