Metadata-Version: 2.1
Name: cvxgraphalgs
Version: 0.1.2
Summary: Modern convex optimization-based graph algorithms.
Home-page: https://github.com/hermish/cvx-graph-algorithms
Author: Hermish Mehta
Author-email: hermishdm@gmail.com
License: UNKNOWN
Keywords: graph algorithms theory convex optimization
Platform: UNKNOWN
Classifier: Programming Language :: Python :: 3
Classifier: License :: OSI Approved :: MIT License
Classifier: Operating System :: OS Independent
